{
    "version": "0.1.1",
    "architecture": {
        "64bit": {
            "url": "https://github.com/suzuki-shunsuke/ghproj/releases/download/v0.1.1/ghproj_windows_amd64.zip",
            "bin": [
                "ghproj.exe"
            ],
            "hash": "a787e6464ff0a96fbdae609c05e712c090506d157e933f9b2a874aa2962c14ee"
        },
        "arm64": {
            "url": "https://github.com/suzuki-shunsuke/ghproj/releases/download/v0.1.1/ghproj_windows_arm64.zip",
            "bin": [
                "ghproj.exe"
            ],
            "hash": "c1929e823caf725645ddda009774e8986206f0c90a0af2961d28346b000ea2ac"
        }
    },
    "license": "MIT",
    "description": "Add GitHub Issues and Pull Requests to GitHub Projects\n"
}